COPYING
MANIFEST.in
README.rst
buildout.cfg
requirements.txt
setup.py
version.txt
bob/__init__.py
bob.db.oulunpu.egg-info/PKG-INFO
bob.db.oulunpu.egg-info/SOURCES.txt
bob.db.oulunpu.egg-info/dependency_links.txt
bob.db.oulunpu.egg-info/entry_points.txt
bob.db.oulunpu.egg-info/requires.txt
bob.db.oulunpu.egg-info/top_level.txt
bob/db/__init__.py
bob/db/oulunpu/__init__.py
bob/db/oulunpu/config.py
bob/db/oulunpu/driver.py
bob/db/oulunpu/query.py
bob/db/oulunpu/test.py
bob/db/oulunpu/lists/Protocol_1/dev/for_attack.lst
bob/db/oulunpu/lists/Protocol_1/dev/for_real.lst
bob/db/oulunpu/lists/Protocol_1/eval/for_attack.lst
bob/db/oulunpu/lists/Protocol_1/eval/for_real.lst
bob/db/oulunpu/lists/Protocol_1/train/for_attack.lst
bob/db/oulunpu/lists/Protocol_1/train/for_real.lst
bob/db/oulunpu/lists/Protocol_1_2/dev/for_attack.lst
bob/db/oulunpu/lists/Protocol_1_2/dev/for_real.lst
bob/db/oulunpu/lists/Protocol_1_2/eval/for_attack.lst
bob/db/oulunpu/lists/Protocol_1_2/eval/for_real.lst
bob/db/oulunpu/lists/Protocol_1_2/train/for_attack.lst
bob/db/oulunpu/lists/Protocol_1_2/train/for_real.lst
bob/db/oulunpu/lists/Protocol_1_3/dev/for_attack.lst
bob/db/oulunpu/lists/Protocol_1_3/dev/for_real.lst
bob/db/oulunpu/lists/Protocol_1_3/eval/for_attack.lst
bob/db/oulunpu/lists/Protocol_1_3/eval/for_real.lst
bob/db/oulunpu/lists/Protocol_1_3/train/for_attack.lst
bob/db/oulunpu/lists/Protocol_1_3/train/for_real.lst
bob/db/oulunpu/lists/Protocol_2/dev/for_attack.lst
bob/db/oulunpu/lists/Protocol_2/dev/for_real.lst
bob/db/oulunpu/lists/Protocol_2/eval/for_attack.lst
bob/db/oulunpu/lists/Protocol_2/eval/for_real.lst
bob/db/oulunpu/lists/Protocol_2/train/for_attack.lst
bob/db/oulunpu/lists/Protocol_2/train/for_real.lst
bob/db/oulunpu/lists/Protocol_3_1/dev/for_attack.lst
bob/db/oulunpu/lists/Protocol_3_1/dev/for_real.lst
bob/db/oulunpu/lists/Protocol_3_1/eval/for_attack.lst
bob/db/oulunpu/lists/Protocol_3_1/eval/for_real.lst
bob/db/oulunpu/lists/Protocol_3_1/train/for_attack.lst
bob/db/oulunpu/lists/Protocol_3_1/train/for_real.lst
bob/db/oulunpu/lists/Protocol_3_2/dev/for_attack.lst
bob/db/oulunpu/lists/Protocol_3_2/dev/for_real.lst
bob/db/oulunpu/lists/Protocol_3_2/eval/for_attack.lst
